<?xml version="1.0" encoding="UTF-8"?>
<ck><di ky="0" rd="about_authorizing_payment_transactions.htm|About Authorizing Payment Transactions" ct=" 	       	 		 		 		 			   GCP CashWeb                                         		 ..."/><di ky="1" rd="account_activity.htm|Account Activity" ct="  	       	 		 		 		 			   GCP CashWeb                                          ..."/><di ky="2" rd="account_auth_name_list.htm|Account Auth Name List" ct=" 	       	 		 		 		 			   GCP CashWeb                                         		 ..."/><di ky="3" rd="account_balance.htm|Account Balance" ct=" 	       	 		 		 		 			   GCP CashWeb                                         		 ..."/><di ky="4" rd="account_balance_history.htm|Account Balance History" ct="  	       	 		 		 		 			   GCP CashWeb                                          ..."/><di ky="5" rd="account_introduction.htm|Account Introduction" ct="  	       	 		 		 		 			   GCP CashWeb                                          ..."/><di ky="6" rd="account_name_edit.htm|Account Name Edit" ct=" 	       	 		 		 		 			   GCP CashWeb                                         		 ..."/><di ky="7" rd="account_name_list.htm|Account Name List" ct=" 	       	 		 		 		 			   GCP CashWeb                                         		 ..."/><di ky="8" rd="account_setup.htm|Account Setup" ct=" 	       	 		 		 		 			   GCP CashWeb                                         		 ..."/><di ky="9" rd="account_setup_auth.htm|Account Setup Auth" ct=" 	       	 		 		 		 			   GCP CashWeb                                         		 ..."/><di ky="10" rd="account_summary.htm|Account Summary" ct="  	       	 		 		 		 			   GCP CashWeb                                          ..."/><di ky="11" rd="admin_setup.htm|Admin Setup" ct=" 	       	 		 		 		 			   GCP CashWeb                                         		 ..."/><di ky="12" rd="auth_matrix_entry.htm|Auth Matrix Entry" ct=" 	       	 		 		 		 			   GCP CashWeb                                         		 ..."/><di ky="13" rd="auth_matrix_list.htm|Auth Matrix List" ct="  	       	 		 		 		 			   GCP CashWeb                                          ..."/><di ky="14" rd="authmatrix_authorization_list.htm|AuthMatrix Authorization List" ct=" 	       	 		 		 		 			   GCP CashWeb                                         		 ..."/><di ky="15" rd="authorizing_a_collection_transaction.htm|Authorizing a Collection Transaction" ct="  	       	 		 		 		 			   GCP CashWeb                                          ..."/><di ky="16" rd="authorizing_a_payment_transaction.htm|Authorizing a Payment Transaction" ct="  	       	 		 		 		 			   GCP CashWeb                                          ..."/><di ky="17" rd="authorizing_a_transaction_si_new.htm|Authorizing a Transaction SI New" ct=" 	       	 		 		 		 			   GCP CashWeb                                         		 ..."/><di ky="18" rd="batch_header.htm|Batch Header" ct="  	       	 		 		 		 			   GCP CashWeb                                          ..."/><di ky="19" rd="batch_header_si_new.htm|Batch Header SI New" ct=" 	       	 		 		 		 			   GCP CashWeb                                         		 ..."/><di ky="20" rd="beneficiaries.htm|Beneficiaries" ct="  	       	 		 		 		 			   GCP CashWeb                                          ..."/><di ky="21" rd="beneficiaries_authorization_list.htm|Beneficiaries Authorization List" ct=" 	       	 		 		 		 			   GCP CashWeb                                         		 ..."/><di ky="22" rd="beneficiary_entry.htm|Beneficiary Entry" ct="  	       	 		 		 		 			   GCP CashWeb                                          ..."/><di ky="23" rd="category_authorization_list.htm|Category Authorization List" ct=" 	       	 		 		 		 			   GCP CashWeb                                         		 ..."/><di ky="24" rd="category_master_entry.htm|Category Master Entry" ct="  	       	 		 		 		 			   GCP CashWeb                                          ..."/><di ky="25" rd="cheque_book_request.htm|Cheque Book Request" ct=" 	       	 		 		 		 			   GCP CashWeb                                         		 ..."/><di ky="26" rd="cheque_book_requests.htm|Cheque Book Requests" ct=" 	       	 		 		 		 			   GCP CashWeb                                         		 ..."/><di ky="27" rd="collection_center.htm|Collection Center" ct="  	       	 		 		 		 			   GCP CashWeb                                          ..."/><di ky="28" rd="collection_file_upload.htm|Collection File Upload" ct=" 	       	 		 		 		 			   GCP CashWeb                                         		 ..."/><di ky="29" rd="collection_masters.htm|Collection Masters" ct=" 	       	 		 		 		 			   GCP CashWeb                                         		 ..."/><di ky="30" rd="collection_my_product_authorization_list.htm|Collection My Product Authorization List" ct=" 	       	 		 		 		 			   GCP CashWeb                                         		 ..."/><di ky="31" rd="collection_my_product_list.htm|Collection My Product List" ct="  	       	 		 		 		 			   GCP CashWeb                                          ..."/><di ky="32" rd="collection_my_product_master_entry.htm|Collection My Product Master Entry" ct=" 	       	 		 		 		 			   GCP CashWeb                                         		 ..."/><di ky="33" rd="collections.htm|Collections" ct=" 	       	 		 		 		 			   GCP CashWeb                                         		 ..."/><di ky="34" rd="collections1.htm|Collections1" ct=" 	       	 		 		 		 			   GCP CashWeb                                         		 ..."/><di ky="35" rd="collections_query.htm|Collections Query" ct=" 	       	 		 		 		 			   GCP CashWeb                                         		 ..."/><di ky="36" rd="common_files.htm|Common Files" ct=" 	       	 		 		 		 			   GCP CashWeb                                         		 ..."/><di ky="37" rd="conventions.htm|Conventions" ct="  	       	 		 		 		 			   GCP CashWeb                                          ..."/><di ky="38" rd="creating_transaction_template.htm|Creating Transaction Template" ct="  	       	 		 		 		 			   GCP CashWeb                                          ..."/><di ky="39" rd="currency_based_authorization_matrix.htm|Currency based authorization matrix" ct=" 	       	 		 		 		 			   GCP CashWeb                                         		 ..."/><di ky="40" rd="customer_upload_download.htm|Customer Upload Download" ct=" 	       	 		 		 		 			   GCP CashWeb                                         		 ..."/><di ky="41" rd="deposit.htm|Deposit" ct=" 	       	 		 		 		 			   GCP CashWeb                                         		 ..."/><di ky="42" rd="deposit_query.htm|Deposit Query" ct=" 	       	 		 		 		 			   GCP CashWeb                                         		 ..."/><di ky="43" rd="download_list.htm|Download List" ct=" 	       	 		 		 		 			   GCP CashWeb                                         		 ..."/><di ky="44" rd="drawer_list.htm|Payer List" ct="  	       	 		 		 		 			   GCP CashWeb                                          ..."/><di ky="45" rd="drawers.htm|Payers" ct="  	       	 		 		 		 			   GCP CashWeb                                          ..."/><di ky="46" rd="drawers_auth.htm|Payers Auth" ct=" 	       	 		 		 		 			   GCP CashWeb                                         		 ..."/><di ky="47" rd="enrichments_authorization.htm|Enrichments Authorization" ct=" 	       	 		 		 		 			   GCP CashWeb                                         		 ..."/><di ky="48" rd="enrichments_entry.htm|Enrichments Entry" ct=" 	       	 		 		 		 			   GCP CashWeb                                         		 ..."/><di ky="49" rd="enrichments_list.htm|Enrichments List" ct=" 	       	 		 		 		 			   GCP CashWeb                                         		 ..."/><di ky="50" rd="file_upload.htm|File Upload" ct="  	       	 		 		 		 			   GCP CashWeb                                          ..."/><di ky="51" rd="file_upload2.htm|File Upload2" ct=" 	       	 		 		 		 			   GCP CashWeb                                         		 ..."/><di ky="52" rd="group_authorization.htm|Group Authorization" ct=" 	       	 		 		 		 			   GCP CashWeb                                         		 ..."/></ck>